<?xml version="1.0"?>
<gameList>
  <folder>
    <path>/home/gabriel/RetroPie/roms/fds/#</path>
    <name>19</name>
    <thumbnail />
    <image />
    <marquee />
    <video />
    <rating />
    <desc />
    <releasedate />
    <developer />
    <publisher />
    <genre />
    <players />
  </folder>
  <game>
    <path>/home/gabriel/RetroPie/roms/fds/A/adian no tsue.zip</path>
    <name>adian no tsue</name>
    <thumbnail />
    <image />
    <marquee />
    <video />
    <rating />
    <desc />
    <releasedate />
    <developer />
    <publisher />
    <genre />
    <players />
  </game>
  <game>
    <path>/home/gabriel/RetroPie/roms/fds/A/Ai Senshi Nicol.fds</path>
    <name>Ai Senshi Nicol</name>
    <thumbnail />
    <image />
    <marquee />
    <video />
    <rating />
    <desc />
    <releasedate />
    <developer />
    <publisher />
    <genre />
    <players />
  </game>
  <game>
    <path>/home/gabriel/RetroPie/roms/fds/A/Aki to Tsukasa no Fushigi no Kabe (UNL).fds</path>
    <name>Aki to Tsukasa no Fushigi no Kabe</name>
    <thumbnail />
    <image />
    <marquee />
    <video />
    <rating />
    <desc />
    <releasedate />
    <developer />
    <publisher />
    <genre />
    <players />
  </game>
  <game>
    <path>/home/gabriel/RetroPie/roms/fds/A/akumajou dracula (hack).zip</path>
    <name>akumajou dracula</name>
    <thumbnail />
    <image />
    <marquee />
    <video />
    <rating />
    <desc />
    <releasedate />
    <developer />
    <publisher />
    <genre />
    <players />
  </game>
  <game>
    <path>/home/gabriel/RetroPie/roms/fds/A/akumajou dracula.zip</path>
    <name>akumajou dracula</name>
    <thumbnail />
    <image />
    <marquee />
    <video />
    <rating />
    <desc />
    <releasedate />
    <developer />
    <publisher />
    <genre />
    <players />
  </game>
  <game>
    <path>/home/gabriel/RetroPie/roms/fds/A/akuu senki raijin.zip</path>
    <name>akuu senki raijin</name>
    <thumbnail />
    <image />
    <marquee />
    <video />
    <rating />
    <desc />
    <releasedate />
    <developer />
    <publisher />
    <genre />
    <players />
  </game>
  <game>
    <path>/home/gabriel/RetroPie/roms/fds/A/all night nippon super mario bros.zip</path>
    <name>all night nippon super mario bros</name>
    <thumbnail />
    <image />
    <marquee />
    <video />
    <rating />
    <desc />
    <releasedate />
    <developer />
    <publisher />
    <genre />
    <players />
  </game>
  <game>
    <path>/home/gabriel/RetroPie/roms/fds/A/all one - famimaga disk vol. 3.zip</path>
    <name>all one - famimaga disk vol. 3</name>
    <thumbnail />
    <image />
    <marquee />
    <video />
    <rating />
    <desc />
    <releasedate />
    <developer />
    <publisher />
    <genre />
    <players />
  </game>
  <game>
    <path>/home/gabriel/RetroPie/roms/fds/A/apple town story - little computer people.zip</path>
    <name>apple town story - little computer people</name>
    <thumbnail />
    <image />
    <marquee />
    <video />
    <rating />
    <desc />
    <releasedate />
    <developer />
    <publisher />
    <genre />
    <players />
  </game>
  <game>
    <path>/home/gabriel/RetroPie/roms/fds/A/arumana no kiseki.zip</path>
    <name>arumana no kiseki</name>
    <thumbnail />
    <image />
    <marquee />
    <video />
    <rating />
    <desc />
    <releasedate />
    <developer />
    <publisher />
    <genre />
    <players />
  </game>
  <game>
    <path>/home/gabriel/RetroPie/roms/fds/A/aspic - majaou no noroi.zip</path>
    <name>aspic - majaou no noroi</name>
    <thumbnail />
    <image />
    <marquee />
    <video />
    <rating />
    <desc />
    <releasedate />
    <developer />
    <publisher />
    <genre />
    <players />
  </game>
  <game>
    <path>/home/gabriel/RetroPie/roms/fds/B/backgammon.zip</path>
    <name>backgammon</name>
    <thumbnail />
    <image />
    <marquee />
    <video />
    <rating />
    <desc />
    <releasedate />
    <developer />
    <publisher />
    <genre />
    <players />
  </game>
  <game>
    <path>/home/gabriel/RetroPie/roms/fds/B/bakutoushi patton kun.zip</path>
    <name>bakutoushi patton kun</name>
    <thumbnail />
    <image />
    <marquee />
    <video />
    <rating />
    <desc />
    <releasedate />
    <developer />
    <publisher />
    <genre />
    <players />
  </game>
  <game>
    <path>/home/gabriel/RetroPie/roms/fds/B/baseball.zip</path>
    <name>baseball</name>
    <thumbnail />
    <image />
    <marquee />
    <video />
    <rating />
    <desc />
    <releasedate />
    <developer />
    <publisher />
    <genre />
    <players />
  </game>
  <game>
    <path>/home/gabriel/RetroPie/roms/fds/B/big challenge! dogfight spirit.zip</path>
    <name>big challenge! dogfight spirit</name>
    <thumbnail />
    <image />
    <marquee />
    <video />
    <rating />
    <desc />
    <releasedate />
    <developer />
    <publisher />
    <genre />
    <players />
  </game>
  <game>
    <path>/home/gabriel/RetroPie/roms/fds/B/big challenge! go! go! bowling.zip</path>
    <name>big challenge! go! go! bowling</name>
    <thumbnail />
    <image />
    <marquee />
    <video />
    <rating />
    <desc />
    <releasedate />
    <developer />
    <publisher />
    <genre />
    <players />
  </game>
  <game>
    <path>/home/gabriel/RetroPie/roms/fds/B/big challenge! gun fighter.zip</path>
    <name>big challenge! gun fighter</name>
    <thumbnail />
    <image />
    <marquee />
    <video />
    <rating />
    <desc />
    <releasedate />
    <developer />
    <publisher />
    <genre />
    <players />
  </game>
  <game>
    <path>/home/gabriel/RetroPie/roms/fds/B/big challenge! juudou senshuken.zip</path>
    <name>big challenge! juudou senshuken</name>
    <thumbnail />
    <image />
    <marquee />
    <video />
    <rating />
    <desc />
    <releasedate />
    <developer />
    <publisher />
    <genre />
    <players />
  </game>
  <game>
    <path>/home/gabriel/RetroPie/roms/fds/B/bio miracle bokutte upa.zip</path>
    <name>bio miracle bokutte upa</name>
    <thumbnail />
    <image />
    <marquee />
    <video />
    <rating />
    <desc />
    <releasedate />
    <developer />
    <publisher />
    <genre />
    <players />
  </game>
  <game>
    <path>/home/gabriel/RetroPie/roms/fds/B/bishoujo control (unl).zip</path>
    <name>bishoujo control</name>
    <thumbnail />
    <image />
    <marquee />
    <video />
    <rating />
    <desc />
    <releasedate />
    <developer />
    <publisher />
    <genre />
    <players />
  </game>
  <game>
    <path>/home/gabriel/RetroPie/roms/fds/B/bishoujo control (unl)(2).zip</path>
    <name>bishoujo control</name>
    <thumbnail />
    <image />
    <marquee />
    <video />
    <rating />
    <desc />
    <releasedate />
    <developer />
    <publisher />
    <genre />
    <players />
  </game>
  <game>
    <path>/home/gabriel/RetroPie/roms/fds/B/bishoujo mahjong club (unl).zip</path>
    <name>bishoujo mahjong club</name>
    <thumbnail />
    <image />
    <marquee />
    <video />
    <rating />
    <desc />
    <releasedate />
    <developer />
    <publisher />
    <genre />
    <players />
  </game>
  <game>
    <path>/home/gabriel/RetroPie/roms/fds/B/bishoujo sexy derby (unl).zip</path>
    <name>bishoujo sexy derby</name>
    <thumbnail />
    <image />
    <marquee />
    <video />
    <rating />
    <desc />
    <releasedate />
    <developer />
    <publisher />
    <genre />
    <players />
  </game>
  <game>
    <path>/home/gabriel/RetroPie/roms/fds/B/bishoujo sf alien battle (unl).zip</path>
    <name>bishoujo sf alien battle</name>
    <thumbnail />
    <image />
    <marquee />
    <video />
    <rating />
    <desc />
    <releasedate />
    <developer />
    <publisher />
    <genre />
    <players />
  </game>
  <game>
    <path>/home/gabriel/RetroPie/roms/fds/B/bishoujo shashinkan - studio cut (unl).zip</path>
    <name>bishoujo shashinkan - studio cut</name>
    <thumbnail />
    <image />
    <marquee />
    <video />
    <rating />
    <desc />
    <releasedate />
    <developer />
    <publisher />
    <genre />
    <players />
  </game>
  <game>
    <path>/home/gabriel/RetroPie/roms/fds/B/bomberman.zip</path>
    <name>bomberman</name>
    <thumbnail />
    <image />
    <marquee />
    <video />
    <rating />
    <desc />
    <releasedate />
    <developer />
    <publisher />
    <genre />
    <players />
  </game>
  <game>
    <path>/home/gabriel/RetroPie/roms/fds/B/breeder.zip</path>
    <name>breeder</name>
    <thumbnail />
    <image />
    <marquee />
    <video />
    <rating />
    <desc />
    <releasedate />
    <developer />
    <publisher />
    <genre />
    <players />
  </game>
  <game>
    <path>/home/gabriel/RetroPie/roms/fds/B/bubble bobble.zip</path>
    <name>bubble bobble</name>
    <thumbnail />
    <image />
    <marquee />
    <video />
    <rating />
    <desc />
    <releasedate />
    <developer />
    <publisher />
    <genre />
    <players />
  </game>
  <game>
    <path>/home/gabriel/RetroPie/roms/fds/B/burger time.zip</path>
    <name>burger time</name>
    <thumbnail />
    <image />
    <marquee />
    <video />
    <rating />
    <desc />
    <releasedate />
    <developer />
    <publisher />
    <genre />
    <players />
  </game>
  <game>
    <path>/home/gabriel/RetroPie/roms/fds/C/casino de pink (unl).zip</path>
    <name>casino de pink</name>
    <thumbnail />
    <image />
    <marquee />
    <video />
    <rating />
    <desc />
    <releasedate />
    <developer />
    <publisher />
    <genre />
    <players />
  </game>
  <game>
    <path>/home/gabriel/RetroPie/roms/fds/C/castlevania_simon%b4s_quest(j).zip</path>
    <name>castlevania simon%b4s quest</name>
    <thumbnail />
    <image />
    <marquee />
    <video />
    <rating />
    <desc />
    <releasedate />
    <developer />
    <publisher />
    <genre />
    <players />
  </game>
  <game>
    <path>/home/gabriel/RetroPie/roms/fds/C/chitei tairiku orudoora.zip</path>
    <name>chitei tairiku orudoora</name>
    <thumbnail />
    <image />
    <marquee />
    <video />
    <rating />
    <desc />
    <releasedate />
    <developer />
    <publisher />
    <genre />
    <players />
  </game>
  <game>
    <path>/home/gabriel/RetroPie/roms/fds/C/city connection (unl).zip</path>
    <name>city connection</name>
    <thumbnail />
    <image />
    <marquee />
    <video />
    <rating />
    <desc />
    <releasedate />
    <developer />
    <publisher />
    <genre />
    <players />
  </game>
  <game>
    <path>/home/gabriel/RetroPie/roms/fds/C/cleopatra no mahou.zip</path>
    <name>cleopatra no mahou</name>
    <thumbnail />
    <image />
    <marquee />
    <video />
    <rating />
    <desc />
    <releasedate />
    <developer />
    <publisher />
    <genre />
    <players />
  </game>
  <game>
    <path>/home/gabriel/RetroPie/roms/fds/C/clox - famimaga disk vol. 4.zip</path>
    <name>clox - famimaga disk vol. 4</name>
    <thumbnail />
    <image />
    <marquee />
    <video />
    <rating />
    <desc />
    <releasedate />
    <developer />
    <publisher />
    <genre />
    <players />
  </game>
  <game>
    <path>/home/gabriel/RetroPie/roms/fds/C/clu clu land - welcome to new cluclu land.zip</path>
    <name>clu clu land - welcome to new cluclu land</name>
    <thumbnail />
    <image />
    <marquee />
    <video />
    <rating />
    <desc />
    <releasedate />
    <developer />
    <publisher />
    <genre />
    <players />
  </game>
  <game>
    <path>/home/gabriel/RetroPie/roms/fds/C/cocona world.zip</path>
    <name>cocona world</name>
    <thumbnail />
    <image />
    <marquee />
    <video />
    <rating />
    <desc />
    <releasedate />
    <developer />
    <publisher />
    <genre />
    <players />
  </game>
  <game>
    <path>/home/gabriel/RetroPie/roms/fds/D/dandy (zeuon no fukkatsu).zip</path>
    <name>dandy</name>
    <thumbnail />
    <image />
    <marquee />
    <video />
    <rating />
    <desc />
    <releasedate />
    <developer />
    <publisher />
    <genre />
    <players />
  </game>
  <game>
    <path>/home/gabriel/RetroPie/roms/fds/D/date de blackjack (unl).zip</path>
    <name>date de blackjack</name>
    <thumbnail />
    <image />
    <marquee />
    <video />
    <rating />
    <desc />
    <releasedate />
    <developer />
    <publisher />
    <genre />
    <players />
  </game>
  <game>
    <path>/home/gabriel/RetroPie/roms/fds/D/dead zone.zip</path>
    <name>dead zone</name>
    <thumbnail />
    <image />
    <marquee />
    <video />
    <rating />
    <desc />
    <releasedate />
    <developer />
    <publisher />
    <genre />
    <players />
  </game>
  <game>
    <path>/home/gabriel/RetroPie/roms/fds/D/deep dungeon (madou senki).zip</path>
    <name>deep dungeon</name>
    <thumbnail />
    <image />
    <marquee />
    <video />
    <rating />
    <desc />
    <releasedate />
    <developer />
    <publisher />
    <genre />
    <players />
  </game>
  <game>
    <path>/home/gabriel/RetroPie/roms/fds/D/dig dug.zip</path>
    <name>dig dug</name>
    <thumbnail />
    <image />
    <marquee />
    <video />
    <rating />
    <desc />
    <releasedate />
    <developer />
    <publisher />
    <genre />
    <players />
  </game>
  <game>
    <path>/home/gabriel/RetroPie/roms/fds/D/dig dug ii.zip</path>
    <name>dig dug ii</name>
    <thumbnail />
    <image />
    <marquee />
    <video />
    <rating />
    <desc />
    <releasedate />
    <developer />
    <publisher />
    <genre />
    <players />
  </game>
  <game>
    <path>/home/gabriel/RetroPie/roms/fds/D/dirty pair - project eden.zip</path>
    <name>dirty pair - project eden</name>
    <thumbnail />
    <image />
    <marquee />
    <video />
    <rating />
    <desc />
    <releasedate />
    <developer />
    <publisher />
    <genre />
    <players />
  </game>
  <game>
    <path>/home/gabriel/RetroPie/roms/fds/D/donkey kong.zip</path>
    <name>donkey kong</name>
    <thumbnail />
    <image />
    <marquee />
    <video />
    <rating />
    <desc />
    <releasedate />
    <developer />
    <publisher />
    <genre />
    <players />
  </game>
  <game>
    <path>/home/gabriel/RetroPie/roms/fds/D/donkey kong jr.zip</path>
    <name>donkey kong jr</name>
    <thumbnail />
    <image />
    <marquee />
    <video />
    <rating />
    <desc />
    <releasedate />
    <developer />
    <publisher />
    <genre />
    <players />
  </game>
  <game>
    <path>/home/gabriel/RetroPie/roms/fds/D/doremikko.zip</path>
    <name>doremikko</name>
    <thumbnail />
    <image />
    <marquee />
    <video />
    <rating />
    <desc />
    <releasedate />
    <developer />
    <publisher />
    <genre />
    <players />
  </game>
  <game>
    <path>/home/gabriel/RetroPie/roms/fds/D/dr. chaos (jigoku no tobira).zip</path>
    <name>dr. chaos</name>
    <thumbnail />
    <image />
    <marquee />
    <video />
    <rating />
    <desc />
    <releasedate />
    <developer />
    <publisher />
    <genre />
    <players />
  </game>
  <game>
    <path>/home/gabriel/RetroPie/roms/fds/D/dracula ii - noroi no fuuin.zip</path>
    <name>dracula ii - noroi no fuuin</name>
    <thumbnail />
    <image />
    <marquee />
    <video />
    <rating />
    <desc />
    <releasedate />
    <developer />
    <publisher />
    <genre />
    <players />
  </game>
  <game>
    <path>/home/gabriel/RetroPie/roms/fds/D/druid - kyoufu no tobira.zip</path>
    <name>druid - kyoufu no tobira</name>
    <thumbnail />
    <image />
    <marquee />
    <video />
    <rating />
    <desc />
    <releasedate />
    <developer />
    <publisher />
    <genre />
    <players />
  </game>
  <game>
    <path>/home/gabriel/RetroPie/roms/fds/E/eggerland.zip</path>
    <name>eggerland</name>
    <thumbnail />
    <image />
    <marquee />
    <video />
    <rating />
    <desc />
    <releasedate />
    <developer />
    <publisher />
    <genre />
    <players />
  </game>
  <game>
    <path>/home/gabriel/RetroPie/roms/fds/E/eggerland - souzou heno tabidachi.zip</path>
    <name>eggerland - souzou heno tabidachi</name>
    <thumbnail />
    <image />
    <marquee />
    <video />
    <rating />
    <desc />
    <releasedate />
    <developer />
    <publisher />
    <genre />
    <players />
  </game>
  <game>
    <path>/home/gabriel/RetroPie/roms/fds/E/electrician.zip</path>
    <name>electrician</name>
    <thumbnail />
    <image />
    <marquee />
    <video />
    <rating />
    <desc />
    <releasedate />
    <developer />
    <publisher />
    <genre />
    <players />
  </game>
  <game>
    <path>/home/gabriel/RetroPie/roms/fds/E/esper dream.zip</path>
    <name>esper dream</name>
    <thumbnail />
    <image />
    <marquee />
    <video />
    <rating />
    <desc />
    <releasedate />
    <developer />
    <publisher />
    <genre />
    <players />
  </game>
  <game>
    <path>/home/gabriel/RetroPie/roms/fds/E/exciting baseball.zip</path>
    <name>exciting baseball</name>
    <thumbnail />
    <image />
    <marquee />
    <video />
    <rating />
    <desc />
    <releasedate />
    <developer />
    <publisher />
    <genre />
    <players />
  </game>
  <game>
    <path>/home/gabriel/RetroPie/roms/fds/E/exciting basket.zip</path>
    <name>exciting basket</name>
    <thumbnail />
    <image />
    <marquee />
    <video />
    <rating />
    <desc />
    <releasedate />
    <developer />
    <publisher />
    <genre />
    <players />
  </game>
  <game>
    <path>/home/gabriel/RetroPie/roms/fds/E/exciting billiard.zip</path>
    <name>exciting billiard</name>
    <thumbnail />
    <image />
    <marquee />
    <video />
    <rating />
    <desc />
    <releasedate />
    <developer />
    <publisher />
    <genre />
    <players />
  </game>
  <game>
    <path>/home/gabriel/RetroPie/roms/fds/E/exciting soccer - konami cup.zip</path>
    <name>exciting soccer - konami cup</name>
    <thumbnail />
    <image />
    <marquee />
    <video />
    <rating />
    <desc />
    <releasedate />
    <developer />
    <publisher />
    <genre />
    <players />
  </game>
  <game>
    <path>/home/gabriel/RetroPie/roms/fds/F/fairytale.zip</path>
    <name>fairytale</name>
    <thumbnail />
    <image />
    <marquee />
    <video />
    <rating />
    <desc />
    <releasedate />
    <developer />
    <publisher />
    <genre />
    <players />
  </game>
  <game>
    <path>/home/gabriel/RetroPie/roms/fds/F/falsion.zip</path>
    <name>falsion</name>
    <thumbnail />
    <image />
    <marquee />
    <video />
    <rating />
    <desc />
    <releasedate />
    <developer />
    <publisher />
    <genre />
    <players />
  </game>
  <game>
    <path>/home/gabriel/RetroPie/roms/fds/F/famicom grand prix - f1 race.zip</path>
    <name>famicom grand prix - f1 race</name>
    <thumbnail />
    <image />
    <marquee />
    <video />
    <rating />
    <desc />
    <releasedate />
    <developer />
    <publisher />
    <genre />
    <players />
  </game>
  <game>
    <path>/home/gabriel/RetroPie/roms/fds/F/famicom grand prix ii - 3d hot rally.zip</path>
    <name>famicom grand prix ii - 3d hot rally</name>
    <thumbnail />
    <image />
    <marquee />
    <video />
    <rating />
    <desc />
    <releasedate />
    <developer />
    <publisher />
    <genre />
    <players />
  </game>
  <game>
    <path>/home/gabriel/RetroPie/roms/fds/F/famicom mukashi banashi - shin onigashima.zip</path>
    <name>famicom mukashi banashi - shin onigashima</name>
    <thumbnail />
    <image />
    <marquee />
    <video />
    <rating />
    <desc />
    <releasedate />
    <developer />
    <publisher />
    <genre />
    <players />
  </game>
  <game>
    <path>/home/gabriel/RetroPie/roms/fds/F/famicom mukashi banashi - yuu yuu ki.zip</path>
    <name>famicom mukashi banashi - yuu yuu ki</name>
    <thumbnail />
    <image />
    <marquee />
    <video />
    <rating />
    <desc />
    <releasedate />
    <developer />
    <publisher />
    <genre />
    <players />
  </game>
  <game>
    <path>/home/gabriel/RetroPie/roms/fds/F/famicom tantei club (kieta koukeisha).zip</path>
    <name>famicom tantei club</name>
    <thumbnail />
    <image />
    <marquee />
    <video />
    <rating />
    <desc />
    <releasedate />
    <developer />
    <publisher />
    <genre />
    <players />
  </game>
  <game>
    <path>/home/gabriel/RetroPie/roms/fds/F/famicom tantei club part ii (ushiro ni tatsu shoujo).zip</path>
    <name>famicom tantei club part ii</name>
    <thumbnail />
    <image />
    <marquee />
    <video />
    <rating />
    <desc />
    <releasedate />
    <developer />
    <publisher />
    <genre />
    <players />
  </game>
  <game>
    <path>/home/gabriel/RetroPie/roms/fds/F/family composer.zip</path>
    <name>family composer</name>
    <thumbnail />
    <image />
    <marquee />
    <video />
    <rating />
    <desc />
    <releasedate />
    <developer />
    <publisher />
    <genre />
    <players />
  </game>
  <game>
    <path>/home/gabriel/RetroPie/roms/fds/F/family computer - golf japan course.zip</path>
    <name>family computer - golf japan course</name>
    <thumbnail />
    <image />
    <marquee />
    <video />
    <rating />
    <desc />
    <releasedate />
    <developer />
    <publisher />
    <genre />
    <players />
  </game>
  <game>
    <path>/home/gabriel/RetroPie/roms/fds/F/family computer - golf u.s. course.zip</path>
    <name>family computer - golf u.s. course</name>
    <thumbnail />
    <image />
    <marquee />
    <video />
    <rating />
    <desc />
    <releasedate />
    <developer />
    <publisher />
    <genre />
    <players />
  </game>
  <game>
    <path>/home/gabriel/RetroPie/roms/fds/F/family computer - othello.zip</path>
    <name>family computer - othello</name>
    <thumbnail />
    <image />
    <marquee />
    <video />
    <rating />
    <desc />
    <releasedate />
    <developer />
    <publisher />
    <genre />
    <players />
  </game>
  <game>
    <path>/home/gabriel/RetroPie/roms/fds/F/final commando - akai yousai.zip</path>
    <name>final commando - akai yousai</name>
    <thumbnail />
    <image />
    <marquee />
    <video />
    <rating />
    <desc />
    <releasedate />
    <developer />
    <publisher />
    <genre />
    <players />
  </game>
  <game>
    <path>/home/gabriel/RetroPie/roms/fds/F/fire bam.zip</path>
    <name>fire bam</name>
    <thumbnail />
    <image />
    <marquee />
    <video />
    <rating />
    <desc />
    <releasedate />
    <developer />
    <publisher />
    <genre />
    <players />
  </game>
  <game>
    <path>/home/gabriel/RetroPie/roms/fds/F/fire rock.zip</path>
    <name>fire rock</name>
    <thumbnail />
    <image />
    <marquee />
    <video />
    <rating />
    <desc />
    <releasedate />
    <developer />
    <publisher />
    <genre />
    <players />
  </game>
  <game>
    <path>/home/gabriel/RetroPie/roms/fds/F/fuuun shourinken.zip</path>
    <name>fuuun shourinken</name>
    <thumbnail />
    <image />
    <marquee />
    <video />
    <rating />
    <desc />
    <releasedate />
    <developer />
    <publisher />
    <genre />
    <players />
  </game>
  <game>
    <path>/home/gabriel/RetroPie/roms/fds/F/fuuun shourinken - ankoku no maou.zip</path>
    <name>fuuun shourinken - ankoku no maou</name>
    <thumbnail />
    <image />
    <marquee />
    <video />
    <rating />
    <desc />
    <releasedate />
    <developer />
    <publisher />
    <genre />
    <players />
  </game>
  <game>
    <path>/home/gabriel/RetroPie/roms/fds/G/galaga.zip</path>
    <name>galaga</name>
    <thumbnail />
    <image />
    <marquee />
    <video />
    <rating />
    <desc />
    <releasedate />
    <developer />
    <publisher />
    <genre />
    <players />
  </game>
  <game>
    <path>/home/gabriel/RetroPie/roms/fds/G/galaxian.zip</path>
    <name>galaxian</name>
    <thumbnail />
    <image />
    <marquee />
    <video />
    <rating />
    <desc />
    <releasedate />
    <developer />
    <publisher />
    <genre />
    <players />
  </game>
  <game>
    <path>/home/gabriel/RetroPie/roms/fds/G/gall force - eternal story.zip</path>
    <name>gall force - eternal story</name>
    <thumbnail />
    <image />
    <marquee />
    <video />
    <rating />
    <desc />
    <releasedate />
    <developer />
    <publisher />
    <genre />
    <players />
  </game>
  <game>
    <path>/home/gabriel/RetroPie/roms/fds/G/game tengoku.zip</path>
    <name>game tengoku</name>
    <thumbnail />
    <image />
    <marquee />
    <video />
    <rating />
    <desc />
    <releasedate />
    <developer />
    <publisher />
    <genre />
    <players />
  </game>
  <game>
    <path>/home/gabriel/RetroPie/roms/fds/G/ginga denshou - galaxy odyssey.zip</path>
    <name>ginga denshou - galaxy odyssey</name>
    <thumbnail />
    <image />
    <marquee />
    <video />
    <rating />
    <desc />
    <releasedate />
    <developer />
    <publisher />
    <genre />
    <players />
  </game>
  <game>
    <path>/home/gabriel/RetroPie/roms/fds/G/golf.zip</path>
    <name>golf</name>
    <thumbnail />
    <image />
    <marquee />
    <video />
    <rating />
    <desc />
    <releasedate />
    <developer />
    <publisher />
    <genre />
    <players />
  </game>
  <game>
    <path>/home/gabriel/RetroPie/roms/fds/G/golf japan course - nyuushou.zip</path>
    <name>golf japan course - nyuushou</name>
    <thumbnail />
    <image />
    <marquee />
    <video />
    <rating />
    <desc />
    <releasedate />
    <developer />
    <publisher />
    <genre />
    <players />
  </game>
  <game>
    <path>/home/gabriel/RetroPie/roms/fds/G/goonies, the.zip</path>
    <name>the goonies</name>
    <thumbnail />
    <image />
    <marquee />
    <video />
    <rating />
    <desc />
    <releasedate />
    <developer />
    <publisher />
    <genre />
    <players />
  </game>
  <game>
    <path>/home/gabriel/RetroPie/roms/fds/G/green beret.zip</path>
    <name>green beret</name>
    <thumbnail />
    <image />
    <marquee />
    <video />
    <rating />
    <desc />
    <releasedate />
    <developer />
    <publisher />
    <genre />
    <players />
  </game>
  <game>
    <path>/home/gabriel/RetroPie/roms/fds/G/green beret (alt).zip</path>
    <name>green beret</name>
    <thumbnail />
    <image />
    <marquee />
    <video />
    <rating />
    <desc />
    <releasedate />
    <developer />
    <publisher />
    <genre />
    <players />
  </game>
  <game>
    <path>/home/gabriel/RetroPie/roms/fds/G/gun.smoke.zip</path>
    <name>gun.smoke</name>
    <thumbnail />
    <image />
    <marquee />
    <video />
    <rating />
    <desc />
    <releasedate />
    <developer />
    <publisher />
    <genre />
    <players />
  </game>
  <game>
    <path>/home/gabriel/RetroPie/roms/fds/G/gyruss.zip</path>
    <name>gyruss</name>
    <thumbnail />
    <image />
    <marquee />
    <video />
    <rating />
    <desc />
    <releasedate />
    <developer />
    <publisher />
    <genre />
    <players />
  </game>
  <game>
    <path>/home/gabriel/RetroPie/roms/fds/H/halley wars.zip</path>
    <name>halley wars</name>
    <thumbnail />
    <image />
    <marquee />
    <video />
    <rating />
    <desc />
    <releasedate />
    <developer />
    <publisher />
    <genre />
    <players />
  </game>
  <game>
    <path>/home/gabriel/RetroPie/roms/fds/H/hao kun no fushigina tabi.zip</path>
    <name>hao kun no fushigina tabi</name>
    <thumbnail />
    <image />
    <marquee />
    <video />
    <rating />
    <desc />
    <releasedate />
    <developer />
    <publisher />
    <genre />
    <players />
  </game>
  <game>
    <path>/home/gabriel/RetroPie/roms/fds/H/hikari shinwa - parutena no kagami.zip</path>
    <name>hikari shinwa - parutena no kagami</name>
    <thumbnail />
    <image />
    <marquee />
    <video />
    <rating />
    <desc />
    <releasedate />
    <developer />
    <publisher />
    <genre />
    <players />
  </game>
  <game>
    <path>/home/gabriel/RetroPie/roms/fds/H/hikaru genji - roller panic.zip</path>
    <name>hikaru genji - roller panic</name>
    <thumbnail />
    <image />
    <marquee />
    <video />
    <rating />
    <desc />
    <releasedate />
    <developer />
    <publisher />
    <genre />
    <players />
  </game>
  <game>
    <path>/home/gabriel/RetroPie/roms/fds/H/hong kong - famimaga disk vol. 1.zip</path>
    <name>hong kong - famimaga disk vol. 1</name>
    <thumbnail />
    <image />
    <marquee />
    <video />
    <rating />
    <desc />
    <releasedate />
    <developer />
    <publisher />
    <genre />
    <players />
  </game>
  <game>
    <path>/home/gabriel/RetroPie/roms/fds/I/i am a teacher (teami no kiso).zip</path>
    <name>i am a teacher</name>
    <thumbnail />
    <image />
    <marquee />
    <video />
    <rating />
    <desc />
    <releasedate />
    <developer />
    <publisher />
    <genre />
    <players />
  </game>
  <game>
    <path>/home/gabriel/RetroPie/roms/fds/I/i am a teacher (super mario no sweater).zip</path>
    <name>i am a teacher</name>
    <thumbnail />
    <image />
    <marquee />
    <video />
    <rating />
    <desc />
    <releasedate />
    <developer />
    <publisher />
    <genre />
    <players />
  </game>
  <game>
    <path>/home/gabriel/RetroPie/roms/fds/I/ice climber.zip</path>
    <name>ice climber</name>
    <thumbnail />
    <image />
    <marquee />
    <video />
    <rating />
    <desc />
    <releasedate />
    <developer />
    <publisher />
    <genre />
    <players />
  </game>
  <game>
    <path>/home/gabriel/RetroPie/roms/fds/I/ice hockey.zip</path>
    <name>ice hockey</name>
    <thumbnail />
    <image />
    <marquee />
    <video />
    <rating />
    <desc />
    <releasedate />
    <developer />
    <publisher />
    <genre />
    <players />
  </game>
  <game>
    <path>/home/gabriel/RetroPie/roms/fds/I/igo (kyuu roban taikyoku).zip</path>
    <name>igo</name>
    <thumbnail />
    <image />
    <marquee />
    <video />
    <rating />
    <desc />
    <releasedate />
    <developer />
    <publisher />
    <genre />
    <players />
  </game>
  <game>
    <path>/home/gabriel/RetroPie/roms/fds/I/ishidou.zip</path>
    <name>ishidou</name>
    <thumbnail />
    <image />
    <marquee />
    <video />
    <rating />
    <desc />
    <releasedate />
    <developer />
    <publisher />
    <genre />
    <players />
  </game>
  <game>
    <path>/home/gabriel/RetroPie/roms/fds/J/jaaman tanteidan marin gumi (maruhi jigoma sousa file).zip</path>
    <name>jaaman tanteidan marin gumi</name>
    <thumbnail />
    <image />
    <marquee />
    <video />
    <rating />
    <desc />
    <releasedate />
    <developer />
    <publisher />
    <genre />
    <players />
  </game>
  <game>
    <path>/home/gabriel/RetroPie/roms/fds/J/janken disk jou - famimaga disk vol. 6.zip</path>
    <name>janken disk jou - famimaga disk vol. 6</name>
    <thumbnail />
    <image />
    <marquee />
    <video />
    <rating />
    <desc />
    <releasedate />
    <developer />
    <publisher />
    <genre />
    <players />
  </game>
  <game>
    <path>/home/gabriel/RetroPie/roms/fds/J/jikai shounen met mag.zip</path>
    <name>jikai shounen met mag</name>
    <thumbnail />
    <image />
    <marquee />
    <video />
    <rating />
    <desc />
    <releasedate />
    <developer />
    <publisher />
    <genre />
    <players />
  </game>
  <game>
    <path>/home/gabriel/RetroPie/roms/fds/K/kaettekita mario bros.zip</path>
    <name>kaettekita mario bros</name>
    <thumbnail />
    <image />
    <marquee />
    <video />
    <rating />
    <desc />
    <releasedate />
    <developer />
    <publisher />
    <genre />
    <players />
  </game>
  <game>
    <path>/home/gabriel/RetroPie/roms/fds/K/kalin no tsurugi.zip</path>
    <name>kalin no tsurugi</name>
    <thumbnail />
    <image />
    <marquee />
    <video />
    <rating />
    <desc />
    <releasedate />
    <developer />
    <publisher />
    <genre />
    <players />
  </game>
  <game>
    <path>/home/gabriel/RetroPie/roms/fds/K/kamen rider black - taiketsu shadow moon.zip</path>
    <name>kamen rider black - taiketsu shadow moon</name>
    <thumbnail />
    <image />
    <marquee />
    <video />
    <rating />
    <desc />
    <releasedate />
    <developer />
    <publisher />
    <genre />
    <players />
  </game>
  <game>
    <path>/home/gabriel/RetroPie/roms/fds/K/karate champ.zip</path>
    <name>karate champ</name>
    <thumbnail />
    <image />
    <marquee />
    <video />
    <rating />
    <desc />
    <releasedate />
    <developer />
    <publisher />
    <genre />
    <players />
  </game>
  <game>
    <path>/home/gabriel/RetroPie/roms/fds/K/kattobi! douji.zip</path>
    <name>kattobi! douji</name>
    <thumbnail />
    <image />
    <marquee />
    <video />
    <rating />
    <desc />
    <releasedate />
    <developer />
    <publisher />
    <genre />
    <players />
  </game>
  <game>
    <path>/home/gabriel/RetroPie/roms/fds/K/kick and run.zip</path>
    <name>kick and run</name>
    <thumbnail />
    <image />
    <marquee />
    <video />
    <rating />
    <desc />
    <releasedate />
    <developer />
    <publisher />
    <genre />
    <players />
  </game>
  <game>
    <path>/home/gabriel/RetroPie/roms/fds/K/kick challenger - air foot (yasai no kuni no ashi senshi).zip</path>
    <name>kick challenger - air foot</name>
    <thumbnail />
    <image />
    <marquee />
    <video />
    <rating />
    <desc />
    <releasedate />
    <developer />
    <publisher />
    <genre />
    <players />
  </game>
  <game>
    <path>/home/gabriel/RetroPie/roms/fds/K/kieta princess.zip</path>
    <name>kieta princess</name>
    <thumbnail />
    <image />
    <marquee />
    <video />
    <rating />
    <desc />
    <releasedate />
    <developer />
    <publisher />
    <genre />
    <players />
  </game>
  <game>
    <path>/home/gabriel/RetroPie/roms/fds/K/kiki kaikai - dotou hen.zip</path>
    <name>kiki kaikai - dotou hen</name>
    <thumbnail />
    <image />
    <marquee />
    <video />
    <rating />
    <desc />
    <releasedate />
    <developer />
    <publisher />
    <genre />
    <players />
  </game>
  <game>
    <path>/home/gabriel/RetroPie/roms/fds/K/kineko - kinetic connection - the monitor puzzle.zip</path>
    <name>kineko - kinetic connection - the monitor puzzle</name>
    <thumbnail />
    <image />
    <marquee />
    <video />
    <rating />
    <desc />
    <releasedate />
    <developer />
    <publisher />
    <genre />
    <players />
  </game>
  <game>
    <path>/home/gabriel/RetroPie/roms/fds/K/kineko - kinetic connection - the monitor puzzle vol. ii.zip</path>
    <name>kineko - kinetic connection - the monitor puzzle vol. ii</name>
    <thumbnail />
    <image />
    <marquee />
    <video />
    <rating />
    <desc />
    <releasedate />
    <developer />
    <publisher />
    <genre />
    <players />
  </game>
  <game>
    <path>/home/gabriel/RetroPie/roms/fds/K/kinnikuman - kinnikusei oui soudatsusen.zip</path>
    <name>kinnikuman - kinnikusei oui soudatsusen</name>
    <thumbnail />
    <image />
    <marquee />
    <video />
    <rating />
    <desc />
    <releasedate />
    <developer />
    <publisher />
    <genre />
    <players />
  </game>
  <game>
    <path>/home/gabriel/RetroPie/roms/fds/K/knight lore (majou no ookami otoko).zip</path>
    <name>knight lore</name>
    <thumbnail />
    <image />
    <marquee />
    <video />
    <rating />
    <desc />
    <releasedate />
    <developer />
    <publisher />
    <genre />
    <players />
  </game>
  <game>
    <path>/home/gabriel/RetroPie/roms/fds/K/knight move.zip</path>
    <name>knight move</name>
    <thumbnail />
    <image />
    <marquee />
    <video />
    <rating />
    <desc />
    <releasedate />
    <developer />
    <publisher />
    <genre />
    <players />
  </game>
  <game>
    <path>/home/gabriel/RetroPie/roms/fds/K/kobayashi hitome no hold up (unl).zip</path>
    <name>kobayashi hitome no hold up</name>
    <thumbnail />
    <image />
    <marquee />
    <video />
    <rating />
    <desc />
    <releasedate />
    <developer />
    <publisher />
    <genre />
    <players />
  </game>
  <game>
    <path>/home/gabriel/RetroPie/roms/fds/K/konamic ice hockey.zip</path>
    <name>konamic ice hockey</name>
    <thumbnail />
    <image />
    <marquee />
    <video />
    <rating />
    <desc />
    <releasedate />
    <developer />
    <publisher />
    <genre />
    <players />
  </game>
  <game>
    <path>/home/gabriel/RetroPie/roms/fds/K/konamic tennis.zip</path>
    <name>konamic tennis</name>
    <thumbnail />
    <image />
    <marquee />
    <video />
    <rating />
    <desc />
    <releasedate />
    <developer />
    <publisher />
    <genre />
    <players />
  </game>
  <game>
    <path>/home/gabriel/RetroPie/roms/fds/K/koneko monogatari - the adventures of chatran.zip</path>
    <name>koneko monogatari - the adventures of chatran</name>
    <thumbnail />
    <image />
    <marquee />
    <video />
    <rating />
    <desc />
    <releasedate />
    <developer />
    <publisher />
    <genre />
    <players />
  </game>
  <game>
    <path>/home/gabriel/RetroPie/roms/fds/L/legend of zelda 2 - link no bouken, the.zip</path>
    <name>the legend of zelda 2 - link no bouken</name>
    <thumbnail />
    <image />
    <marquee />
    <video />
    <rating />
    <desc />
    <releasedate />
    <developer />
    <publisher />
    <genre />
    <players />
  </game>
  <game>
    <path>/home/gabriel/RetroPie/roms/fds/L/lutter.zip</path>
    <name>lutter</name>
    <thumbnail />
    <image />
    <marquee />
    <video />
    <rating />
    <desc />
    <releasedate />
    <developer />
    <publisher />
    <genre />
    <players />
  </game>
  <game>
    <path>/home/gabriel/RetroPie/roms/fds/M/magma project hacker.zip</path>
    <name>magma project hacker</name>
    <thumbnail />
    <image />
    <marquee />
    <video />
    <rating />
    <desc />
    <releasedate />
    <developer />
    <publisher />
    <genre />
    <players />
  </game>
  <game>
    <path>/home/gabriel/RetroPie/roms/fds/M/mahjong (chr2).zip</path>
    <name>mahjong</name>
    <thumbnail />
    <image />
    <marquee />
    <video />
    <rating />
    <desc />
    <releasedate />
    <developer />
    <publisher />
    <genre />
    <players />
  </game>
  <game>
    <path>/home/gabriel/RetroPie/roms/fds/M/mahjong (chr1).zip</path>
    <name>mahjong</name>
    <thumbnail />
    <image />
    <marquee />
    <video />
    <rating />
    <desc />
    <releasedate />
    <developer />
    <publisher />
    <genre />
    <players />
  </game>
  <game>
    <path>/home/gabriel/RetroPie/roms/fds/M/mahjong kazoku.zip</path>
    <name>mahjong kazoku</name>
    <thumbnail />
    <image />
    <marquee />
    <video />
    <rating />
    <desc />
    <releasedate />
    <developer />
    <publisher />
    <genre />
    <players />
  </game>
  <game>
    <path>/home/gabriel/RetroPie/roms/fds/M/marchen veil.zip</path>
    <name>marchen veil</name>
    <thumbnail />
    <image />
    <marquee />
    <video />
    <rating />
    <desc />
    <releasedate />
    <developer />
    <publisher />
    <genre />
    <players />
  </game>
  <game>
    <path>/home/gabriel/RetroPie/roms/fds/M/mario bobble (hack).zip</path>
    <name>mario bobble</name>
    <thumbnail />
    <image />
    <marquee />
    <video />
    <rating />
    <desc />
    <releasedate />
    <developer />
    <publisher />
    <genre />
    <players />
  </game>
  <game>
    <path>/home/gabriel/RetroPie/roms/fds/M/matou no houkai - the hero of babel.zip</path>
    <name>matou no houkai - the hero of babel</name>
    <thumbnail />
    <image />
    <marquee />
    <video />
    <rating />
    <desc />
    <releasedate />
    <developer />
    <publisher />
    <genre />
    <players />
  </game>
  <game>
    <path>/home/gabriel/RetroPie/roms/fds/M/meikyuu jiin dababa.zip</path>
    <name>meikyuu jiin dababa</name>
    <thumbnail />
    <image />
    <marquee />
    <video />
    <rating />
    <desc />
    <releasedate />
    <developer />
    <publisher />
    <genre />
    <players />
  </game>
  <game>
    <path>/home/gabriel/RetroPie/roms/fds/M/metroid.zip</path>
    <name>metroid</name>
    <thumbnail />
    <image />
    <marquee />
    <video />
    <rating />
    <desc />
    <releasedate />
    <developer />
    <publisher />
    <genre />
    <players />
  </game>
  <game>
    <path>/home/gabriel/RetroPie/roms/fds/M/michael english dai bouken.zip</path>
    <name>michael english dai bouken</name>
    <thumbnail />
    <image />
    <marquee />
    <video />
    <rating />
    <desc />
    <releasedate />
    <developer />
    <publisher />
    <genre />
    <players />
  </game>
  <game>
    <path>/home/gabriel/RetroPie/roms/fds/M/moero twinbee - cinnamon hakase wo sukue!.zip</path>
    <name>moero twinbee - cinnamon hakase wo sukue!</name>
    <thumbnail />
    <image />
    <marquee />
    <video />
    <rating />
    <desc />
    <releasedate />
    <developer />
    <publisher />
    <genre />
    <players />
  </game>
  <game>
    <path>/home/gabriel/RetroPie/roms/fds/M/moero yakyuuken (unl).zip</path>
    <name>moero yakyuuken</name>
    <thumbnail />
    <image />
    <marquee />
    <video />
    <rating />
    <desc />
    <releasedate />
    <developer />
    <publisher />
    <genre />
    <players />
  </game>
  <game>
    <path>/home/gabriel/RetroPie/roms/fds/M/monty no doki doki dai dassou.zip</path>
    <name>monty no doki doki dai dassou</name>
    <thumbnail />
    <image />
    <marquee />
    <video />
    <rating />
    <desc />
    <releasedate />
    <developer />
    <publisher />
    <genre />
    <players />
  </game>
  <game>
    <path>/home/gabriel/RetroPie/roms/fds/M/moonball magic.zip</path>
    <name>moonball magic</name>
    <thumbnail />
    <image />
    <marquee />
    <video />
    <rating />
    <desc />
    <releasedate />
    <developer />
    <publisher />
    <genre />
    <players />
  </game>
  <game>
    <path>/home/gabriel/RetroPie/roms/fds/M/mr gold - kinsan in the space (tooyama no kinsan space chou).zip</path>
    <name>mr gold - kinsan in the space</name>
    <thumbnail />
    <image />
    <marquee />
    <video />
    <rating />
    <desc />
    <releasedate />
    <developer />
    <publisher />
    <genre />
    <players />
  </game>
  <game>
    <path>/home/gabriel/RetroPie/roms/fds/N/nakayama miho no tokimeki high school.zip</path>
    <name>nakayama miho no tokimeki high school</name>
    <thumbnail />
    <image />
    <marquee />
    <video />
    <rating />
    <desc />
    <releasedate />
    <developer />
    <publisher />
    <genre />
    <players />
  </game>
  <game>
    <path>/home/gabriel/RetroPie/roms/fds/N/nakayama miho no tokimeki high school(2).zip</path>
    <name>nakayama miho no tokimeki high school</name>
    <thumbnail />
    <image />
    <marquee />
    <video />
    <rating />
    <desc />
    <releasedate />
    <developer />
    <publisher />
    <genre />
    <players />
  </game>
  <game>
    <path>/home/gabriel/RetroPie/roms/fds/N/nankin no adobenchia.zip</path>
    <name>nankin no adobenchia</name>
    <thumbnail />
    <image />
    <marquee />
    <video />
    <rating />
    <desc />
    <releasedate />
    <developer />
    <publisher />
    <genre />
    <players />
  </game>
  <game>
    <path>/home/gabriel/RetroPie/roms/fds/N/nazo no kabe - block kuzushi.zip</path>
    <name>nazo no kabe - block kuzushi</name>
    <thumbnail />
    <image />
    <marquee />
    <video />
    <rating />
    <desc />
    <releasedate />
    <developer />
    <publisher />
    <genre />
    <players />
  </game>
  <game>
    <path>/home/gabriel/RetroPie/roms/fds/N/nazo no magazine disk - nazoraa land dai 2 gou.zip</path>
    <name>nazo no magazine disk - nazoraa land dai 2 gou</name>
    <thumbnail />
    <image />
    <marquee />
    <video />
    <rating />
    <desc />
    <releasedate />
    <developer />
    <publisher />
    <genre />
    <players />
  </game>
  <game>
    <path>/home/gabriel/RetroPie/roms/fds/N/nazo no magazine disk - nazoraa land dai 3 gou.zip</path>
    <name>nazo no magazine disk - nazoraa land dai 3 gou</name>
    <thumbnail />
    <image />
    <marquee />
    <video />
    <rating />
    <desc />
    <releasedate />
    <developer />
    <publisher />
    <genre />
    <players />
  </game>
  <game>
    <path>/home/gabriel/RetroPie/roms/fds/N/nazo no magazine disk - nazoraa land soukan gou.zip</path>
    <name>nazo no magazine disk - nazoraa land soukan gou</name>
    <thumbnail />
    <image />
    <marquee />
    <video />
    <rating />
    <desc />
    <releasedate />
    <developer />
    <publisher />
    <genre />
    <players />
  </game>
  <game>
    <path>/home/gabriel/RetroPie/roms/fds/N/nazo no magazine disk - nazoraa land zoukan gou - quiz ou wo sagase!.zip</path>
    <name>nazo no magazine disk - nazoraa land zoukan gou - quiz ou wo sagase!</name>
    <thumbnail />
    <image />
    <marquee />
    <video />
    <rating />
    <desc />
    <releasedate />
    <developer />
    <publisher />
    <genre />
    <players />
  </game>
  <game>
    <path>/home/gabriel/RetroPie/roms/fds/N/nazo no murasamejou.zip</path>
    <name>nazo no murasamejou</name>
    <thumbnail />
    <image />
    <marquee />
    <video />
    <rating />
    <desc />
    <releasedate />
    <developer />
    <publisher />
    <genre />
    <players />
  </game>
  <game>
    <path>/home/gabriel/RetroPie/roms/fds/O/omoikkiri tanteidan haado gumi - matenrou no chousenjou.zip</path>
    <name>omoikkiri tanteidan haado gumi - matenrou no chousenjou</name>
    <thumbnail />
    <image />
    <marquee />
    <video />
    <rating />
    <desc />
    <releasedate />
    <developer />
    <publisher />
    <genre />
    <players />
  </game>
  <game>
    <path>/home/gabriel/RetroPie/roms/fds/O/otocky.zip</path>
    <name>otocky</name>
    <thumbnail />
    <image />
    <marquee />
    <video />
    <rating />
    <desc />
    <releasedate />
    <developer />
    <publisher />
    <genre />
    <players />
  </game>
  <game>
    <path>/home/gabriel/RetroPie/roms/fds/P/pachi com.zip</path>
    <name>pachi com</name>
    <thumbnail />
    <image />
    <marquee />
    <video />
    <rating />
    <desc />
    <releasedate />
    <developer />
    <publisher />
    <genre />
    <players />
  </game>
  <game>
    <path>/home/gabriel/RetroPie/roms/fds/P/pachinko grand prix.zip</path>
    <name>pachinko grand prix</name>
    <thumbnail />
    <image />
    <marquee />
    <video />
    <rating />
    <desc />
    <releasedate />
    <developer />
    <publisher />
    <genre />
    <players />
  </game>
  <game>
    <path>/home/gabriel/RetroPie/roms/fds/P/panic space - famimaga disk vol. 2.zip</path>
    <name>panic space - famimaga disk vol. 2</name>
    <thumbnail />
    <image />
    <marquee />
    <video />
    <rating />
    <desc />
    <releasedate />
    <developer />
    <publisher />
    <genre />
    <players />
  </game>
  <game>
    <path>/home/gabriel/RetroPie/roms/fds/P/pat pat golf.zip</path>
    <name>pat pat golf</name>
    <thumbnail />
    <image />
    <marquee />
    <video />
    <rating />
    <desc />
    <releasedate />
    <developer />
    <publisher />
    <genre />
    <players />
  </game>
  <game>
    <path>/home/gabriel/RetroPie/roms/fds/P/patlabor - mobile police (kidou keisatsu patlabor).zip</path>
    <name>patlabor - mobile police</name>
    <thumbnail />
    <image />
    <marquee />
    <video />
    <rating />
    <desc />
    <releasedate />
    <developer />
    <publisher />
    <genre />
    <players />
  </game>
  <game>
    <path>/home/gabriel/RetroPie/roms/fds/P/pinball.zip</path>
    <name>pinball</name>
    <thumbnail />
    <image />
    <marquee />
    <video />
    <rating />
    <desc />
    <releasedate />
    <developer />
    <publisher />
    <genre />
    <players />
  </game>
  <game>
    <path>/home/gabriel/RetroPie/roms/fds/P/pro golfer saru - kage no tournament.zip</path>
    <name>pro golfer saru - kage no tournament</name>
    <thumbnail />
    <image />
    <marquee />
    <video />
    <rating />
    <desc />
    <releasedate />
    <developer />
    <publisher />
    <genre />
    <players />
  </game>
  <game>
    <path>/home/gabriel/RetroPie/roms/fds/P/pulsar no hikari - space wars simulation.zip</path>
    <name>pulsar no hikari - space wars simulation</name>
    <thumbnail />
    <image />
    <marquee />
    <video />
    <rating />
    <desc />
    <releasedate />
    <developer />
    <publisher />
    <genre />
    <players />
  </game>
  <game>
    <path>/home/gabriel/RetroPie/roms/fds/P/puroresu - famicom wrestling association.zip</path>
    <name>puroresu - famicom wrestling association</name>
    <thumbnail />
    <image />
    <marquee />
    <video />
    <rating />
    <desc />
    <releasedate />
    <developer />
    <publisher />
    <genre />
    <players />
  </game>
  <game>
    <path>/home/gabriel/RetroPie/roms/fds/P/puyo puyo - famimaga disk vol. 5.zip</path>
    <name>puyo puyo - famimaga disk vol. 5</name>
    <thumbnail />
    <image />
    <marquee />
    <video />
    <rating />
    <desc />
    <releasedate />
    <developer />
    <publisher />
    <genre />
    <players />
  </game>
  <game>
    <path>/home/gabriel/RetroPie/roms/fds/P/puzzle boys.zip</path>
    <name>puzzle boys</name>
    <thumbnail />
    <image />
    <marquee />
    <video />
    <rating />
    <desc />
    <releasedate />
    <developer />
    <publisher />
    <genre />
    <players />
  </game>
  <game>
    <path>/home/gabriel/RetroPie/roms/fds/R/radical bomber!! jirai kun.zip</path>
    <name>radical bomber!! jirai kun</name>
    <thumbnail />
    <image />
    <marquee />
    <video />
    <rating />
    <desc />
    <releasedate />
    <developer />
    <publisher />
    <genre />
    <players />
  </game>
  <game>
    <path>/home/gabriel/RetroPie/roms/fds/R/reflect world.zip</path>
    <name>reflect world</name>
    <thumbnail />
    <image />
    <marquee />
    <video />
    <rating />
    <desc />
    <releasedate />
    <developer />
    <publisher />
    <genre />
    <players />
  </game>
  <game>
    <path>/home/gabriel/RetroPie/roms/fds/R/relics - ankoku yousai.zip</path>
    <name>relics - ankoku yousai</name>
    <thumbnail />
    <image />
    <marquee />
    <video />
    <rating />
    <desc />
    <releasedate />
    <developer />
    <publisher />
    <genre />
    <players />
  </game>
  <game>
    <path>/home/gabriel/RetroPie/roms/fds/R/replicart.zip</path>
    <name>replicart</name>
    <thumbnail />
    <image />
    <marquee />
    <video />
    <rating />
    <desc />
    <releasedate />
    <developer />
    <publisher />
    <genre />
    <players />
  </game>
  <game>
    <path>/home/gabriel/RetroPie/roms/fds/R/risa no yousei densetsu - risa tachibana.zip</path>
    <name>risa no yousei densetsu - risa tachibana</name>
    <thumbnail />
    <image />
    <marquee />
    <video />
    <rating />
    <desc />
    <releasedate />
    <developer />
    <publisher />
    <genre />
    <players />
  </game>
  <game>
    <path>/home/gabriel/RetroPie/roms/fds/R/roger rabbit.zip</path>
    <name>roger rabbit</name>
    <thumbnail />
    <image />
    <marquee />
    <video />
    <rating />
    <desc />
    <releasedate />
    <developer />
    <publisher />
    <genre />
    <players />
  </game>
  <game>
    <path>/home/gabriel/RetroPie/roms/fds/S/sailor fuku bishoujo zukan vol. 1 (unl).zip</path>
    <name>sailor fuku bishoujo zukan vol. 1</name>
    <thumbnail />
    <image />
    <marquee />
    <video />
    <rating />
    <desc />
    <releasedate />
    <developer />
    <publisher />
    <genre />
    <players />
  </game>
  <game>
    <path>/home/gabriel/RetroPie/roms/fds/S/sailor fuku bishoujo zukan vol. 3 (unl).zip</path>
    <name>sailor fuku bishoujo zukan vol. 3</name>
    <thumbnail />
    <image />
    <marquee />
    <video />
    <rating />
    <desc />
    <releasedate />
    <developer />
    <publisher />
    <genre />
    <players />
  </game>
  <game>
    <path>/home/gabriel/RetroPie/roms/fds/S/sailor fuku bishoujo zukan vol. 5 (unl).zip</path>
    <name>sailor fuku bishoujo zukan vol. 5</name>
    <thumbnail />
    <image />
    <marquee />
    <video />
    <rating />
    <desc />
    <releasedate />
    <developer />
    <publisher />
    <genre />
    <players />
  </game>
  <game>
    <path>/home/gabriel/RetroPie/roms/fds/S/sailor fuku bishoujo zukan vol. 6 (unl).zip</path>
    <name>sailor fuku bishoujo zukan vol. 6</name>
    <thumbnail />
    <image />
    <marquee />
    <video />
    <rating />
    <desc />
    <releasedate />
    <developer />
    <publisher />
    <genre />
    <players />
  </game>
  <game>
    <path>/home/gabriel/RetroPie/roms/fds/S/samurai sword.zip</path>
    <name>samurai sword</name>
    <thumbnail />
    <image />
    <marquee />
    <video />
    <rating />
    <desc />
    <releasedate />
    <developer />
    <publisher />
    <genre />
    <players />
  </game>
  <game>
    <path>/home/gabriel/RetroPie/roms/fds/S/santa claus no takarabako.zip</path>
    <name>santa claus no takarabako</name>
    <thumbnail />
    <image />
    <marquee />
    <video />
    <rating />
    <desc />
    <releasedate />
    <developer />
    <publisher />
    <genre />
    <players />
  </game>
  <game>
    <path>/home/gabriel/RetroPie/roms/fds/S/sd gundam world - gachapon senshi - scramble wars (sg1).zip</path>
    <name>sd gundam world - gachapon senshi - scramble wars</name>
    <thumbnail />
    <image />
    <marquee />
    <video />
    <rating />
    <desc />
    <releasedate />
    <developer />
    <publisher />
    <genre />
    <players />
  </game>
  <game>
    <path>/home/gabriel/RetroPie/roms/fds/S/sd gundam world - gachapon senshi - scramble wars (sgw).zip</path>
    <name>sd gundam world - gachapon senshi - scramble wars</name>
    <thumbnail />
    <image />
    <marquee />
    <video />
    <rating />
    <desc />
    <releasedate />
    <developer />
    <publisher />
    <genre />
    <players />
  </game>
  <game>
    <path>/home/gabriel/RetroPie/roms/fds/S/section-z.zip</path>
    <name>section-z</name>
    <thumbnail />
    <image />
    <marquee />
    <video />
    <rating />
    <desc />
    <releasedate />
    <developer />
    <publisher />
    <genre />
    <players />
  </game>
  <game>
    <path>/home/gabriel/RetroPie/roms/fds/S/seiken saikokaribaa (majuu no mori densetsu).zip</path>
    <name>seiken saikokaribaa</name>
    <thumbnail />
    <image />
    <marquee />
    <video />
    <rating />
    <desc />
    <releasedate />
    <developer />
    <publisher />
    <genre />
    <players />
  </game>
  <game>
    <path>/home/gabriel/RetroPie/roms/fds/S/silviana (ai ippai no boukensha).zip</path>
    <name>silviana</name>
    <thumbnail />
    <image />
    <marquee />
    <video />
    <rating />
    <desc />
    <releasedate />
    <developer />
    <publisher />
    <genre />
    <players />
  </game>
  <game>
    <path>/home/gabriel/RetroPie/roms/fds/S/smash ping-pong.zip</path>
    <name>smash ping-pong</name>
    <thumbnail />
    <image />
    <marquee />
    <video />
    <rating />
    <desc />
    <releasedate />
    <developer />
    <publisher />
    <genre />
    <players />
  </game>
  <game>
    <path>/home/gabriel/RetroPie/roms/fds/S/soccer.zip</path>
    <name>soccer</name>
    <thumbnail />
    <image />
    <marquee />
    <video />
    <rating />
    <desc />
    <releasedate />
    <developer />
    <publisher />
    <genre />
    <players />
  </game>
  <game>
    <path>/home/gabriel/RetroPie/roms/fds/S/solomon no kagi.zip</path>
    <name>solomon no kagi</name>
    <thumbnail />
    <image />
    <marquee />
    <video />
    <rating />
    <desc />
    <releasedate />
    <developer />
    <publisher />
    <genre />
    <players />
  </game>
  <game>
    <path>/home/gabriel/RetroPie/roms/fds/S/suishou no dragon.zip</path>
    <name>suishou no dragon</name>
    <thumbnail />
    <image />
    <marquee />
    <video />
    <rating />
    <desc />
    <releasedate />
    <developer />
    <publisher />
    <genre />
    <players />
  </game>
  <game>
    <path>/home/gabriel/RetroPie/roms/fds/S/super boy allan.zip</path>
    <name>super boy allan</name>
    <thumbnail />
    <image />
    <marquee />
    <video />
    <rating />
    <desc />
    <releasedate />
    <developer />
    <publisher />
    <genre />
    <players />
  </game>
  <game>
    <path>/home/gabriel/RetroPie/roms/fds/S/super lode runner.zip</path>
    <name>super lode runner</name>
    <thumbnail />
    <image />
    <marquee />
    <video />
    <rating />
    <desc />
    <releasedate />
    <developer />
    <publisher />
    <genre />
    <players />
  </game>
  <game>
    <path>/home/gabriel/RetroPie/roms/fds/S/super lode runner ii.zip</path>
    <name>super lode runner ii</name>
    <thumbnail />
    <image />
    <marquee />
    <video />
    <rating />
    <desc />
    <releasedate />
    <developer />
    <publisher />
    <genre />
    <players />
  </game>
  <game>
    <path>/home/gabriel/RetroPie/roms/fds/S/super mario bros.zip</path>
    <name>super mario bros</name>
    <thumbnail />
    <image />
    <marquee />
    <video />
    <rating />
    <desc />
    <releasedate />
    <developer />
    <publisher />
    <genre />
    <players />
  </game>
  <game>
    <path>/home/gabriel/RetroPie/roms/fds/S/super mario bros 2.zip</path>
    <name>super mario bros 2</name>
    <thumbnail />
    <image />
    <marquee />
    <video />
    <rating />
    <desc />
    <releasedate />
    <developer />
    <publisher />
    <genre />
    <players />
  </game>
  <game>
    <path>/home/gabriel/RetroPie/roms/fds/S/super mario funky disk (hack).zip</path>
    <name>super mario funky disk</name>
    <thumbnail />
    <image />
    <marquee />
    <video />
    <rating />
    <desc />
    <releasedate />
    <developer />
    <publisher />
    <genre />
    <players />
  </game>
  <game>
    <path>/home/gabriel/RetroPie/roms/fds/T/tanigawa kouji no shougi shinan ii (tsume shougi).zip</path>
    <name>tanigawa kouji no shougi shinan ii</name>
    <thumbnail />
    <image />
    <marquee />
    <video />
    <rating />
    <desc />
    <releasedate />
    <developer />
    <publisher />
    <genre />
    <players />
  </game>
  <game>
    <path>/home/gabriel/RetroPie/roms/fds/T/tantei jinguuji saburou - kikenna futari.zip</path>
    <name>tantei jinguuji saburou - kikenna futari</name>
    <thumbnail />
    <image />
    <marquee />
    <video />
    <rating />
    <desc />
    <releasedate />
    <developer />
    <publisher />
    <genre />
    <players />
  </game>
  <game>
    <path>/home/gabriel/RetroPie/roms/fds/T/tantei jinguuji saburou - shinjuku chuuou kouen satsujin jiken.zip</path>
    <name>tantei jinguuji saburou - shinjuku chuuou kouen satsujin jiken</name>
    <thumbnail />
    <image />
    <marquee />
    <video />
    <rating />
    <desc />
    <releasedate />
    <developer />
    <publisher />
    <genre />
    <players />
  </game>
  <game>
    <path>/home/gabriel/RetroPie/roms/fds/T/tarot uranai.zip</path>
    <name>tarot uranai</name>
    <thumbnail />
    <image />
    <marquee />
    <video />
    <rating />
    <desc />
    <releasedate />
    <developer />
    <publisher />
    <genre />
    <players />
  </game>
  <game>
    <path>/home/gabriel/RetroPie/roms/fds/T/tennis (chr1).zip</path>
    <name>tennis</name>
    <thumbnail />
    <image />
    <marquee />
    <video />
    <rating />
    <desc />
    <releasedate />
    <developer />
    <publisher />
    <genre />
    <players />
  </game>
  <game>
    <path>/home/gabriel/RetroPie/roms/fds/T/tennis (chr2).zip</path>
    <name>tennis</name>
    <thumbnail />
    <image />
    <marquee />
    <video />
    <rating />
    <desc />
    <releasedate />
    <developer />
    <publisher />
    <genre />
    <players />
  </game>
  <game>
    <path>/home/gabriel/RetroPie/roms/fds/T/tennis (chr3).zip</path>
    <name>tennis</name>
    <thumbnail />
    <image />
    <marquee />
    <video />
    <rating />
    <desc />
    <releasedate />
    <developer />
    <publisher />
    <genre />
    <players />
  </game>
  <game>
    <path>/home/gabriel/RetroPie/roms/fds/T/time twist - rekishi no katasume de.zip</path>
    <name>time twist - rekishi no katasume de</name>
    <thumbnail />
    <image />
    <marquee />
    <video />
    <rating />
    <desc />
    <releasedate />
    <developer />
    <publisher />
    <genre />
    <players />
  </game>
  <game>
    <path>/home/gabriel/RetroPie/roms/fds/T/titanic mystery (ao no senritsu).zip</path>
    <name>titanic mystery</name>
    <thumbnail />
    <image />
    <marquee />
    <video />
    <rating />
    <desc />
    <releasedate />
    <developer />
    <publisher />
    <genre />
    <players />
  </game>
  <game>
    <path>/home/gabriel/RetroPie/roms/fds/T/tobidase daisakusen.zip</path>
    <name>tobidase daisakusen</name>
    <thumbnail />
    <image />
    <marquee />
    <video />
    <rating />
    <desc />
    <releasedate />
    <developer />
    <publisher />
    <genre />
    <players />
  </game>
  <game>
    <path>/home/gabriel/RetroPie/roms/fds/T/topple zip.zip</path>
    <name>topple zip</name>
    <thumbnail />
    <image />
    <marquee />
    <video />
    <rating />
    <desc />
    <releasedate />
    <developer />
    <publisher />
    <genre />
    <players />
  </game>
  <game>
    <path>/home/gabriel/RetroPie/roms/fds/T/transformer - the head masters.zip</path>
    <name>transformer - the head masters</name>
    <thumbnail />
    <image />
    <marquee />
    <video />
    <rating />
    <desc />
    <releasedate />
    <developer />
    <publisher />
    <genre />
    <players />
  </game>
  <game>
    <path>/home/gabriel/RetroPie/roms/fds/T/twinbee.zip</path>
    <name>twinbee</name>
    <thumbnail />
    <image />
    <marquee />
    <video />
    <rating />
    <desc />
    <releasedate />
    <developer />
    <publisher />
    <genre />
    <players />
  </game>
  <game>
    <path>/home/gabriel/RetroPie/roms/fds/U/ultraman - kaijuu teikoku no gyakushuu.zip</path>
    <name>ultraman - kaijuu teikoku no gyakushuu</name>
    <thumbnail />
    <image />
    <marquee />
    <video />
    <rating />
    <desc />
    <releasedate />
    <developer />
    <publisher />
    <genre />
    <players />
  </game>
  <game>
    <path>/home/gabriel/RetroPie/roms/fds/U/ultraman 2 - shutsugeki katoku tai.zip</path>
    <name>ultraman 2 - shutsugeki katoku tai</name>
    <thumbnail />
    <image />
    <marquee />
    <video />
    <rating />
    <desc />
    <releasedate />
    <developer />
    <publisher />
    <genre />
    <players />
  </game>
  <game>
    <path>/home/gabriel/RetroPie/roms/fds/U/ultraman club (chikyuu dakkan sakusen).zip</path>
    <name>ultraman club</name>
    <thumbnail />
    <image />
    <marquee />
    <video />
    <rating />
    <desc />
    <releasedate />
    <developer />
    <publisher />
    <genre />
    <players />
  </game>
  <game>
    <path>/home/gabriel/RetroPie/roms/fds/V/volleyball.zip</path>
    <name>volleyball</name>
    <thumbnail />
    <image />
    <marquee />
    <video />
    <rating />
    <desc />
    <releasedate />
    <developer />
    <publisher />
    <genre />
    <players />
  </game>
  <game>
    <path>/home/gabriel/RetroPie/roms/fds/V/vs. excitebike.zip</path>
    <name>vs. excitebike</name>
    <thumbnail />
    <image />
    <marquee />
    <video />
    <rating />
    <desc />
    <releasedate />
    <developer />
    <publisher />
    <genre />
    <players />
  </game>
  <game>
    <path>/home/gabriel/RetroPie/roms/fds/W/wardner no mori.zip</path>
    <name>wardner no mori</name>
    <thumbnail />
    <image />
    <marquee />
    <video />
    <rating />
    <desc />
    <releasedate />
    <developer />
    <publisher />
    <genre />
    <players />
  </game>
  <game>
    <path>/home/gabriel/RetroPie/roms/fds/W/winter games.zip</path>
    <name>winter games</name>
    <thumbnail />
    <image />
    <marquee />
    <video />
    <rating />
    <desc />
    <releasedate />
    <developer />
    <publisher />
    <genre />
    <players />
  </game>
  <game>
    <path>/home/gabriel/RetroPie/roms/fds/W/wrecking crew.zip</path>
    <name>wrecking crew</name>
    <thumbnail />
    <image />
    <marquee />
    <video />
    <rating />
    <desc />
    <releasedate />
    <developer />
    <publisher />
    <genre />
    <players />
  </game>
  <folder>
    <path>/home/gabriel/RetroPie/roms/fds/X</path>
    <name>xevious</name>
    <thumbnail />
    <image />
    <marquee />
    <video />
    <rating />
    <desc />
    <releasedate />
    <developer />
    <publisher />
    <genre />
    <players />
  </folder>
  <game>
    <path>/home/gabriel/RetroPie/roms/fds/Y/youkai yashiki.zip</path>
    <name>youkai yashiki</name>
    <thumbnail />
    <image />
    <marquee />
    <video />
    <rating />
    <desc />
    <releasedate />
    <developer />
    <publisher />
    <genre />
    <players />
  </game>
  <game>
    <path>/home/gabriel/RetroPie/roms/fds/Y/yume koujou doki doki panic.zip</path>
    <name>yume koujou doki doki panic</name>
    <thumbnail />
    <image />
    <marquee />
    <video />
    <rating />
    <desc />
    <releasedate />
    <developer />
    <publisher />
    <genre />
    <players />
  </game>
  <game>
    <path>/home/gabriel/RetroPie/roms/fds/Y/yuu maze.zip</path>
    <name>yuu maze</name>
    <thumbnail />
    <image />
    <marquee />
    <video />
    <rating />
    <desc />
    <releasedate />
    <developer />
    <publisher />
    <genre />
    <players />
  </game>
  <game>
    <path>/home/gabriel/RetroPie/roms/fds/Y/yuushi no monshou (deep dungeon).zip</path>
    <name>yuushi no monshou</name>
    <thumbnail />
    <image />
    <marquee />
    <video />
    <rating />
    <desc />
    <releasedate />
    <developer />
    <publisher />
    <genre />
    <players />
  </game>
  <game>
    <path>/home/gabriel/RetroPie/roms/fds/Z/zanac.zip</path>
    <name>zanac</name>
    <thumbnail />
    <image />
    <marquee />
    <video />
    <rating />
    <desc />
    <releasedate />
    <developer />
    <publisher />
    <genre />
    <players />
  </game>
  <game>
    <path>/home/gabriel/RetroPie/roms/fds/Z/zatsugaku olympic part ii (unl).zip</path>
    <name>zatsugaku olympic part ii</name>
    <thumbnail />
    <image />
    <marquee />
    <video />
    <rating />
    <desc />
    <releasedate />
    <developer />
    <publisher />
    <genre />
    <players />
  </game>
  <game>
    <path>/home/gabriel/RetroPie/roms/fds/Z/zelda no densetsu - the hyrule fantasy.zip</path>
    <name>zelda no densetsu - the hyrule fantasy</name>
    <thumbnail />
    <image />
    <marquee />
    <video />
    <rating />
    <desc />
    <releasedate />
    <developer />
    <publisher />
    <genre />
    <players />
  </game>
</gameList>